ban/__init__.py
ban/nanian/__init__.py
ban/nanian/test.py
nanian_Ly-1.0.0.dist-info/METADATA
nanian_Ly-1.0.0.dist-info/WHEEL
nanian_Ly-1.0.0.dist-info/top_level.txt
nanian_Ly-1.0.0.dist-info/RECORD
