Metadata-Version: 2.1
Name: nanian-Ly
Version: 1.0.0
Summary: This group is composed of one student that is author
Home-page: UNKNOWN
Author: 那年
Author-email: 1009689491@qq.com
License: UNKNOWN
Platform: UNKNOWN
